[
  {
    "field_name": "Cure_Root",
    "id": 1,
    "name": "Cure Root",
    "description_fr": "Racine d'une herbe revigorante. R\u00e9tablit 50 HP.",
    "effects": [
      {
        "target": "SELF",
        "type": "MODIFIER",
        "modifier": "HP",
        "value": 50
      }
    ],
    "description": "Restores 50 HP"
  },
  {
    "field_name": "Cure_Bulb",
    "id": 2,
    "name": "Cure Bulb",
    "description_fr": "Bulbe d'une plante vivifiante. Restaure 100 HP.",
    "effects": [
      {
        "target": "SELF",
        "type": "MODIFIER",
        "modifier": "HP",
        "value": 100
      }
    ],
    "description": "Restores 100 HP"
  },
  {
    "field_name": "Cure_Tonic",
    "id": 3,
    "name": "Cure Tonic",
    "description_fr": "Extrait d'une plante rajeunissante. R\u00e9tablit 150 HP.",
    "effects": [
      {
        "target": "SELF",
        "type": "MODIFIER",
        "modifier": "HP",
        "value": 150
      }
    ],
    "description": "Restores 150 HP"
  },
  {
    "field_name": "Elixir_of_Queens",
    "id": 4,
    "name": "Elixir of Queens",
    "description_fr": "Potion v\u00e9g\u00e9tale reconstituante. Restaure tous les HP.",
    "effects": [
      {
        "target": "SELF",
        "type": "MODIFIER",
        "modifier": "HP",
        "value": 32767
      }
    ],
    "description": "Adds a few points of HP"
  },
  {
    "field_name": "Mana_Root",
    "id": 5,
    "name": "Mana Root",
    "description_fr": "Racine d'une herbe stimulant l'intelligence. R\u00e9tablit 25 MP.",
    "effects": [
      {
        "target": "SELF",
        "type": "MODIFIER",
        "modifier": "MP",
        "value": 25
      }
    ],
    "description": "Restores 25 MP"
  },
  {
    "field_name": "Mana_Bulb",
    "id": 6,
    "name": "Mana Bulb",
    "description_fr": "Bulbe d'une plante stimulant l'intelligence. Recharge 50 MP.",
    "effects": [
      {
        "target": "SELF",
        "type": "MODIFIER",
        "modifier": "MP",
        "value": 50
      }
    ],
    "description": "Restores 50 MP"
  },
  {
    "field_name": "Mana_Tonic",
    "id": 7,
    "name": "Mana Tonic",
    "description_fr": "Extrait de plante vivifiant l'intelligence. R\u00e9tablit 100 MP.",
    "effects": [
      {
        "target": "SELF",
        "type": "MODIFIER",
        "modifier": "MP",
        "value": 100
      }
    ],
    "description": "Restores 150 MP"
  },
  {
    "field_name": "Elixir_of_Kings",
    "id": 8,
    "name": "Elixir of Kings",
    "description_fr": "Potion v\u00e9g\u00e9tale stimulant l'intelligence. Recharge tous les MP.",
    "effects": [
      {
        "target": "SELF",
        "type": "MODIFIER",
        "modifier": "MP",
        "value": 32767
      }
    ],
    "description": "Adds a few points of Strength"
  },
  {
    "field_name": "Vera_Root",
    "id": 9,
    "name": "Vera Root",
    "description_fr": "Racine stimulant le syst\u00e8me nerveux. R\u00e9duit les Risks de 25 points.",
    "effects": [
      {
        "target": "SELF",
        "type": "MODIFIER",
        "modifier": "RISK",
        "value": -25
      }
    ],
    "description": "Lowers RISK by 25"
  },
  {
    "field_name": "Vera_Bulb",
    "id": 10,
    "name": "Vera Bulb",
    "description_fr": "Bulbe qui stimule le syst\u00e8me nerveux. R\u00e9duit les Risks de 50 points.",
    "effects": [
      {
        "target": "SELF",
        "type": "MODIFIER",
        "modifier": "RISK",
        "value": -50
      }
    ],
    "description": "Lowers RISK by 50"
  },
  {
    "field_name": "Vera_Tonic",
    "id": 11,
    "name": "Vera Tonic",
    "description_fr": "Extrait v\u00e9g\u00e9tal stimulant le syst\u00e8me nerveux. R\u00e9duit les Risks de 75 points.",
    "effects": [
      {
        "target": "SELF",
        "type": "MODIFIER",
        "modifier": "RISK",
        "value": -75
      }
    ],
    "description": "Lowers RISK by 150"
  },
  {
    "field_name": "Elixir_of_Sages",
    "id": 12,
    "name": "Elixir of Sages",
    "description_fr": "Potion v\u00e9g\u00e9tale vivifiant le syst\u00e8me nerveux. R\u00e9duit les Risks \u00e0 0.",
    "effects": [
      {
        "target": "SELF",
        "type": "MODIFIER",
        "modifier": "RISK",
        "value": 32767
      }
    ],
    "description": "Adds a few points of Intelligence"
  },
  {
    "field_name": "Faerie_Wing",
    "id": 13,
    "name": "Faerie Wing",
    "description_fr": "Antidote des seigneurs de L\u00e9aMundis. Restaure 100 HP et MP.",
    "effects": [
      {
        "target": "SELF",
        "type": "MODIFIER",
        "modifier": "HP",
        "value": 100
      },
      {
        "target": "SELF",
        "type": "MODIFIER",
        "modifier": "MP",
        "value": 100
      }
    ],
    "description": "Temporarily increases speed and jumps"
  },
  {
    "field_name": "Angelic_Paean",
    "id": 14,
    "name": "Angelic Paean",
    "description_fr": "Antidote c\u00e9leste. R\u00e9tablit tous les HP et MP.",
    "effects": [
      {
        "target": "SELF",
        "type": "MODIFIER",
        "modifier": "HP",
        "value": 32767
      },
      {
        "target": "SELF",
        "type": "MODIFIER",
        "modifier": "MP",
        "value": 32767
      }
    ],
    "description": "Cures Curse"
  },
  {
    "field_name": "Snowfly_Draught",
    "id": 16,
    "name": "Snowfly Draught",
    "description_fr": "R\u00e9actif d'anciens sorciers bafou\u00e9s. Restaure 50 HP, r\u00e9duit les Risks de 50 points.",
    "effects": [
      {
        "target": "SELF",
        "type": "MODIFIER",
        "modifier": "HP",
        "value": 50
      },
      {
        "target": "SELF",
        "type": "MODIFIER",
        "modifier": "RISK",
        "value": -50
      }
    ],
    "description": "Cancels magical effects cast on target"
  },
  {
    "field_name": "Alchemists_Reagent",
    "id": 17,
    "name": "Alchemist's Reagent",
    "description_fr": "Mixture d'ailes de lucioles s\u00e9ch\u00e9es. Annule tous les sortil\u00e8ges.",
    "effects": [],
    "description": "Restores 25 HP / lowers RISK by 25"
  },
  {
    "field_name": "Yggdrasils_Tears",
    "id": 18,
    "name": "Yggdrasil's Tears",
    "description_fr": "Poudre des f\u00e9es acc\u00e9l\u00e9rant les mouvements et rallongeant temporairement les sauts.",
    "effects": [],
    "description": "Cures Paralysis"
  },
  {
    "field_name": "Panacea",
    "id": 20,
    "name": "Panacea",
    "description_fr": "Elixir des Inquisiteurs Royaux. Augmente niveau total: INT (Intelligence).",
    "effects": [
      {
        "target": "SELF",
        "type": "PERMA_MOD",
        "modifier": "INT",
        "value": "ItemEffect.Roll(4"
      }
    ],
    "description": "Cures Paralysis / Poison / Numbness"
  },
  {
    "field_name": "Sorcerers_Reagent",
    "id": 23,
    "name": "Sorcerer's Reagent",
    "description_fr": "Elixir jadis utilis\u00e9 par les mages. Augmente le niveau total de vos MP.",
    "effects": [
      {
        "target": "SELF",
        "type": "PERMA_MOD",
        "modifier": "MP",
        "value": "ItemEffect.Roll(4"
      }
    ],
    "description": "Restores 50 HP / lowers RISK by 50"
  },
  {
    "field_name": "Eye_of_Argon",
    "id": 24,
    "name": "Eye of Argon",
    "description_fr": "Vin rouge de L\u00e9aMundis, d\u00e9licat mais fort en bouche.",
    "effects": [
      {
        "target": "SELF",
        "type": "PERMA_MOD",
        "modifier": "STR",
        "value": "ItemEffect.Roll(4"
      }
    ],
    "description": "Temporarily allows Ashley to see traps"
  },
  {
    "field_name": "Gold_Key",
    "id": 26,
    "name": "Gold Key",
    "description_fr": "Vin blanc des vignes de L\u00e9aMundis, r\u00e9put\u00e9 pour son odeur de miel.",
    "effects": [
      {
        "target": "SELF",
        "type": "PERMA_MOD",
        "modifier": "AGI",
        "value": "ItemEffect.Roll(4"
      }
    ],
    "description": ""
  },
  {
    "field_name": "Silver_Key",
    "id": 27,
    "name": "Silver Key",
    "description_fr": "Vin doux de grande qualit\u00e9.",
    "effects": [
      {
        "target": "SELF",
        "type": "PERMA_MOD",
        "modifier": "HP",
        "value": "ItemEffect.Roll(4"
      }
    ],
    "description": ""
  },
  {
    "field_name": "Bronze_Key",
    "id": 28,
    "name": "Bronze Key",
    "description_fr": "Vin p\u00e9tillant, tir\u00e9 d'un m\u00e9lange de trois c\u00e9l\u00e8bres c\u00e9pages.",
    "effects": [
      {
        "target": "SELF",
        "type": "PERMA_MOD",
        "modifier": "MP",
        "value": "ItemEffect.Roll(4"
      }
    ],
    "description": ""
  },
  {
    "field_name": "Iron_Key",
    "id": 29,
    "name": "Iron Key",
    "description_fr": "R\u00e9v\u00e8le tous les pi\u00e8ges d'une pi\u00e8ce, pendant un bref instant.",
    "effects": [],
    "description": ""
  },
  {
    "field_name": "Cure_Potion",
    "name": "Cure Potion",
    "description": "Restores all HP",
    "game_id": 0,
    "description_fr": "",
    "effects": null
  },
  {
    "field_name": "Mana_Potion",
    "name": "Mana Potion",
    "description": "Restores all MP",
    "game_id": 0,
    "description_fr": "",
    "effects": null
  },
  {
    "field_name": "Vera_Potion",
    "name": "Vera Potion",
    "description": "Clears all RISK",
    "game_id": 0,
    "description_fr": "",
    "effects": null
  },
  {
    "field_name": "Acolytes_Nostrum",
    "name": "Acolyte's Nostrum",
    "description": "Restores 100 HP / MP",
    "game_id": 0,
    "description_fr": "",
    "effects": null
  },
  {
    "field_name": "Saints_Nostrum",
    "name": "Saint's Nostrum",
    "description": "Restores all HP / MP",
    "game_id": 0,
    "description_fr": "",
    "effects": null
  },
  {
    "field_name": "Faerie_Chortle",
    "name": "Faerie Chortle",
    "description": "Cures Poison",
    "game_id": 0,
    "description_fr": "",
    "effects": null
  },
  {
    "field_name": "Spirit_Orison",
    "name": "Spirit Orison",
    "description": "Cures Numbness",
    "game_id": 0,
    "description_fr": "",
    "effects": null
  },
  {
    "field_name": "Elixir_of_Mages",
    "name": "Elixir of Mages",
    "description": "Adds a few points of MP",
    "game_id": 0,
    "description_fr": "",
    "effects": null
  },
  {
    "field_name": "Elixir_of_Dragoons",
    "name": "Elixir of Dragoons",
    "description": "Adds a few points of Agility",
    "game_id": 0,
    "description_fr": "",
    "effects": null
  },
  {
    "field_name": "Audentia",
    "name": "Audentia",
    "description": "Adds a few points of HP",
    "game_id": 0,
    "description_fr": "",
    "effects": null
  },
  {
    "field_name": "Virtus",
    "name": "Virtus",
    "description": "Adds a few points of MP",
    "game_id": 0,
    "description_fr": "",
    "effects": null
  },
  {
    "field_name": "Valens",
    "name": "Valens",
    "description": "Adds a few points of Strength",
    "game_id": 0,
    "description_fr": "",
    "effects": null
  },
  {
    "field_name": "Prudens",
    "name": "Prudens",
    "description": "Adds a few points of Intelligence",
    "game_id": 0,
    "description_fr": "",
    "effects": null
  },
  {
    "field_name": "Volare",
    "name": "Volare",
    "description": "Adds a few points of Agility",
    "game_id": 0,
    "description_fr": "",
    "effects": null
  }
]